ccm_clang_tools/LICENSE
ccm_clang_tools/LLVM-LICENSE
ccm_clang_tools/__init__.py
ccm_clang_tools/build_plugin.py
ccm_clang_tools/clang_parse.py
ccm_clang_tools/get_clang_tool.py
ccm_clang_tools/utils.py
ccm_clang_tools-0.1.0.dist-info/entry_points.txt
ccm_clang_tools-0.1.0.dist-info/WHEEL
ccm_clang_tools-0.1.0.dist-info/METADATA
ccm_clang_tools-0.1.0.dist-info/LICENSE
ccm_clang_tools-0.1.0.dist-info/RECORD
