Metadata-Version: 2.1
Name: ccm-clang-tools
Version: 0.1.0
Summary: CCModel clang plugin
License: MIT
Author-email: Gabriel Ingram <gabriel.ingram@colorado.edu>
Requires-Python: >=3.8
Classifier: License :: OSI Approved :: MIT License
Classifier: Programming Language :: Python :: 3
Classifier: Programming Language :: Python :: 3.8
Classifier: Programming Language :: Python :: 3.9
Project-URL: homepage, https://github.com/gjingram/clang_tools
